timeflux_brainflow/__init__.py
timeflux_brainflow/nodes/__init__.py
timeflux_brainflow/nodes/driver.py
timeflux_brainflow-0.8.0.dist-info/LICENSE
timeflux_brainflow-0.8.0.dist-info/METADATA
timeflux_brainflow-0.8.0.dist-info/WHEEL
timeflux_brainflow-0.8.0.dist-info/top_level.txt
timeflux_brainflow-0.8.0.dist-info/RECORD
